torchdeq/__init__.py
torchdeq/core.py
torchdeq/dropout.py
torchdeq/grad.py
torchdeq/loss/__init__.py
torchdeq/loss/correction.py
torchdeq/loss/jacobian.py
torchdeq/norm/__init__.py
torchdeq/norm/base_norm.py
torchdeq/norm/spectral_norm.py
torchdeq/norm/weight_norm.py
torchdeq/solver/__init__.py
torchdeq/solver/anderson.py
torchdeq/solver/broyden.py
torchdeq/solver/fp_iter.py
torchdeq/solver/stat.py
torchdeq/solver/utils.py
torchdeq/utils/__init__.py
torchdeq/utils/arg_utils.py
torchdeq/utils/config.py
torchdeq/utils/init.py
torchdeq/utils/layer_utils.py
torchdeq/utils/mem.py
torchdeq-0.1.0.dist-info/LICENSE
torchdeq-0.1.0.dist-info/METADATA
torchdeq-0.1.0.dist-info/WHEEL
torchdeq-0.1.0.dist-info/top_level.txt
torchdeq-0.1.0.dist-info/RECORD
