Metadata-Version: 2.1
Name: torchdeq
Version: 0.1.0
Summary: A PyTorch Lib for DEQs
Home-page: https://github.com/locuslab/torchdeq
Author: Zhengyang Geng
Author-email: zhengyanggeng@gmail.com
License: MIT
Classifier: License :: OSI Approved :: MIT License
Classifier: Intended Audience :: Science/Research
Classifier: Topic :: Scientific/Engineering :: Mathematics
Classifier: Topic :: Scientific/Engineering :: Artificial Intelligence
Classifier: Programming Language :: Python :: 3
Classifier: Operating System :: OS Independent
License-File: LICENSE
Requires-Dist: torch (>=1.11.0)
Requires-Dist: numpy (>=1.21.5)
